ws/gitpersona/__init__.py
ws/gitpersona/persona.py
ws/gitpersona/tests/__init__.py
ws/gitpersona/tests/test_persona.py
ws.gitpersona-1.1.0.dist-info/METADATA
ws.gitpersona-1.1.0.dist-info/WHEEL
ws.gitpersona-1.1.0.dist-info/entry_points.txt
ws.gitpersona-1.1.0.dist-info/licenses/LICENSE
ws.gitpersona-1.1.0.dist-info/RECORD
