Metadata-Version: 2.1
Name: ws.gitpersona
Version: 1.1.0
Summary: Provides an easy way to configure git username on a per repository basis
Project-URL: Repository, https://github.com/wosc/git-persona
Author-email: Wolfgang Schnerring <wosc@wosc.de>
License:  BSD-3-Clause
License-File: LICENSE
Requires-Python: >=3.7
Provides-Extra: test
Requires-Dist: pytest; extra == 'test'
Requires-Dist: pytest-cov; extra == 'test'
